[
    {
      "name": "Salada de Atum",
      "description": "Alface, tomate, cebola roxa, atum, azeitonas, molho de vinagrete.",
      "imagePath": "assets/img/mocks/salads/salad_tuna.png",
      "price": 17.99,
      "category": "saladas",
      "availableAddons": [
        {"name": "Ovo cozido", "price": 1.50},
        {"name": "Milho", "price": 1.00},
        {"name": "Pimentão", "price": 1.50}
      ]
    },
    {
      "name": "Salada de Frango",
      "description": "Alface, tomate, cebola roxa, frango grelhado, croutons, molho Caesar.",
      "imagePath": "assets/img/mocks/salads/salad_chicken.png",
      "price": 18.99,
      "category": "saladas",
      "availableAddons": [
        {"name": "Bacon", "price": 2.50},
        {"name": "Queijo parmesão", "price": 2.00},
        {"name": "Azeitonas", "price": 1.50}
      ]
    },
    {
      "name": "Salada de Frutas",
      "description": "Frutas frescas da estação: uma variedade deliciosa e nutritiva para desfrutar a qualquer momento.",
      "imagePath": "assets/img/mocks/salads/salad_fruit.png",
      "price": 14.99,
      "category": "saladas",
      "availableAddons": [
        {"name": "Mel", "price": 1.00},
        {"name": "Iogurte", "price": 2.00},
        {"name": "Granola", "price": 1.50}
      ]
    },
    {
      "name": "Salada Caprese",
      "description": "Tomate, mozzarella, manjericão, azeite e sal: uma explosão de sabores clássicos da culinária italiana.",
      "imagePath": "assets/img/mocks/salads/salad_caprese.png",
      "price": 16.99,
      "category": "saladas",
      "availableAddons": [
        {"name": "Azeitonas", "price": 1.50},
        {"name": "Pimentão", "price": 1.50},
        {"name": "Frango grelhado", "price": 3.00}
      ]
    },
    {
      "name": "Salada de Quinoa",
      "description": "Quinoa, tomate, pepino, cebola roxa, azeitonas, molho de vinagrete.",
      "imagePath": "assets/img/mocks/salads/salad_quinoa.png",
      "price": 19.99,
      "category": "saladas",
      "availableAddons": [
        {"name": "Frango grelhado", "price": 3.00},
        {"name": "Queijo feta", "price": 2.50},
        {"name": "Abacate", "price": 2.00}
      ]
    },
    {
      "name": "Salada de Beterraba",
      "description": "Salada de beterraba, cenoura, alface e nozes, com um toque irresistível de molho de vinagrete.",
      "imagePath": "assets/img/mocks/salads/salad_beetroot.png",
      "price": 15.99,
      "category": "saladas",
      "availableAddons": [
        {"name": "Queijo de cabra", "price": 3.00},
        {"name": "Maçã", "price": 1.50},
        {"name": "Frango grelhado", "price": 3.00}
      ]
    },
    {
      "name": "Salada Caesar",
      "description": "Alface romana, croutons, queijo parmesão, molho Caesar.",
      "imagePath": "assets/img/mocks/salads/salad_caesar.png",
      "price": 15.99,
      "category": "saladas",
      "availableAddons": [
        {"name": "Frango grelhado", "price": 3.00},
        {"name": "Bacon", "price": 2.50},
        {"name": "Ovo cozido", "price": 1.50}
      ]
    },
    {
      "name": "Salada Grega",
      "description": "Tomate, pepino, cebola roxa, azeitonas, queijo feta, molho de vinagrete.",
      "imagePath": "assets/img/mocks/salads/salad_greek.png",
      "price": 16.99,
      "category": "saladas",
      "availableAddons": [
        {"name": "Frango grelhado", "price": 3.00},
        {"name": "Peito de peru", "price": 3.00},
        {"name": "Pimentão", "price": 1.50}
      ]
    }
  ]
  